megaflow/__init__.py
megaflow/context.py
megaflow/exceptions.py
megaflow/resources.py
megaflow/types.py
megaflow-0.1.1.dist-info/METADATA
megaflow-0.1.1.dist-info/WHEEL
megaflow-0.1.1.dist-info/top_level.txt
megaflow-0.1.1.dist-info/RECORD
