Metadata-Version: 2.4
Name: megaflow
Version: 0.1.1
Summary: Megaflow function SDK
Author: Megaflow Team
License: Proprietary
Requires-Python: >=3.10
